<?xml version="1.0" encoding="utf-8" ?>
<Defs>

  <BiomeDef>
    <defName>BMT_CrystalCaverns</defName>
    <label>crystal caverns</label>
    <description>A crystal cave system</description>
    <workerClass>BiomesKit.UniversalBiomeWorker</workerClass>
    <!-- <workerClass>BiomesCaverns.BiomeWorker_NoTest</workerClass> -->
	<modExtensions>
        <li Class="BiomesCore.DefModExtensions.BiomesMap">
			<isCavern>true</isCavern>
			<cavernShapes>
				<li>Smooth</li>
			</cavernShapes>
		</li>
		<li Class="BiomesKit.BiomesKitControls">
			<spawnOnBiomes>
			  <li>BorealForest</li>
			  <li>Tundra</li>
			</spawnOnBiomes>
			<randomizeHilliness>True</randomizeHilliness>
			<minimumLandNeighbors>4</minimumLandNeighbors>
			<allowOnLand>true</allowOnLand>
			<frequency>100</frequency>
			<minTemperature>-44.5</minTemperature>
			<maxTemperature>5.5</maxTemperature>
			<usePerlin>true</usePerlin>
			<perlinCulling>1.0</perlinCulling>
		</li>
	</modExtensions>
    <animalDensity>1.8</animalDensity>
    <plantDensity>0.3</plantDensity>
    <settlementSelectionWeight>0.8</settlementSelectionWeight>
    <movementDifficulty>0.5</movementDifficulty>
    <texture>BMT_Caverns/World/Biomes/CrystalCavern</texture>
    <forageability>0.5</forageability>
    <foragedFood>BMT_RawDulcis</foragedFood>
    <wildPlantRegrowDays>27</wildPlantRegrowDays>
    <soundsAmbient>
      <li>BMT_Ambient_FungalForest</li>
    </soundsAmbient>
    <diseaseMtbDays>40</diseaseMtbDays>
	<diseases>
	  <li>
		<diseaseInc>Disease_Flu</diseaseInc>
		<commonality>100</commonality>
	  </li>
	  <li>
		<diseaseInc>Disease_Plague</diseaseInc>
		<commonality>100</commonality>
	  </li>
	  <li>
		<diseaseInc>Disease_Malaria</diseaseInc>
		<commonality>100</commonality>
	  </li>
	  <li>
		<diseaseInc>Disease_GutWorms</diseaseInc>
		<commonality>50</commonality>
	  </li>
	  <li>
		<diseaseInc>Disease_FibrousMechanites</diseaseInc>
		<commonality>30</commonality>
	  </li>
	  <li>
		<diseaseInc>Disease_SensoryMechanites</diseaseInc>
		<commonality>30</commonality>
	  </li>
	  <li>
		<diseaseInc>Disease_MuscleParasites</diseaseInc>
		<commonality>50</commonality>
	  </li>
	  <li>
		<diseaseInc>Disease_AnimalFlu</diseaseInc>
		<commonality>100</commonality>
	  </li>
	  <li>
		<diseaseInc>Disease_AnimalPlague</diseaseInc>
		<commonality>100</commonality>
	  </li>
	</diseases>
	<terrainsByFertility>
      <!-- <li> -->
        <!-- <terrain>Soil</terrain> -->
        <!-- <min>-999</min> -->
        <!-- <max>0.87</max> -->
      <!-- </li> -->
      <!-- <li> -->
        <!-- <terrain>SoilRich</terrain> -->
        <!-- <min>0.87</min> -->
        <!-- <max>999</max> -->
      <!-- </li> -->
      <li>
        <terrain>Gravel</terrain>
        <min>-999</min>
        <max>0.87</max>
      </li>
      <li>
        <terrain>Sand</terrain>
        <min>0.87</min>
        <max>999</max>
      </li>
    </terrainsByFertility>
    <terrainPatchMakers>
      <li>
        <perlinFrequency>0.035</perlinFrequency>
        <thresholds>
          <li>
            <terrain>Soil</terrain>
            <min>0.63</min>
            <max>0.83</max>
          </li>
          <li>
            <terrain>WaterShallow</terrain>
            <min>0.83</min>
            <max>999</max>
          </li>
        </thresholds>
      </li>
    </terrainPatchMakers>
    <baseWeatherCommonalities>
      <BMT_Calm>100</BMT_Calm>
    </baseWeatherCommonalities>
    <wildPlants>
	<!-- ground cover -->
		<!-- <BMT_FloorMold>1.0</BMT_FloorMold> -->
		
	<!-- mid sized -->

	<!-- trees -->
		
	<!-- other harvestable -->
    
	<!-- hydrophytes -->

	<!-- special -->

    </wildPlants>

    <wildAnimals>
		<!-- herbivores -->
		<!-- <Rat>1.3</Rat> -->
		<BMT_Crystalope>0.8</BMT_Crystalope>
		
		<!-- onmnivore -->
		<BMT_CrystalCrab_Sandstone>0.08</BMT_CrystalCrab_Sandstone>
		<BMT_CrystalCrab_Granite>0.08</BMT_CrystalCrab_Granite>
		<BMT_CrystalCrab_Limestone>0.08</BMT_CrystalCrab_Limestone>
		<BMT_CrystalCrab_Slate>0.08</BMT_CrystalCrab_Slate>
		<BMT_CrystalCrab_Marble>0.08</BMT_CrystalCrab_Marble>
		<BMT_CrystalCrab_Jade>0.01</BMT_CrystalCrab_Jade>
		<BMT_CrystalCrab_Coral MayRequire="biomesteam.biomesislands">0.06</BMT_CrystalCrab_Coral>
	
		<!-- predators -->
	
    </wildAnimals>
    <allowedPackAnimals>
      <li>Muffalo</li>
      <li>Alpaca</li>
	  <li>BMT_GiantSnail</li>
    </allowedPackAnimals>
  </BiomeDef>

</Defs>
